README.rst
setup.cfg
setup.py
./__init__.py
./channel.py
./channel.xml
./product.py
./product.xml
./sale.py
./sale.xml
./tryton.cfg
./user.py
./user.xml
./wizard.py
./wizard.xml
./tests/__init__.py
./tests/test_sale_channel.py
./tests/test_views_depends.py
./view/channel_exception_form.xml
./view/channel_exception_tree.xml
./view/order_states_form.xml
./view/order_states_tree.xml
./view/product_channel_listing_form.xml
./view/product_channel_listing_tree.xml
./view/product_form.xml
./view/sale_channel_form.xml
./view/sale_channel_tree.xml
./view/sale_form.xml
./view/sale_tree.xml
./view/user_form.xml
./view/user_form_preferences.xml
./view/wizard_export_prices_start_form.xml
./view/wizard_export_prices_status_form.xml
./view/wizard_import_data_properties_form.xml
./view/wizard_import_data_start_form.xml
./view/wizard_import_data_success_form.xml
./view/wizard_import_order_states_start_form.xml
openlabs_sale_channel.egg-info/PKG-INFO
openlabs_sale_channel.egg-info/SOURCES.txt
openlabs_sale_channel.egg-info/dependency_links.txt
openlabs_sale_channel.egg-info/entry_points.txt
openlabs_sale_channel.egg-info/not-zip-safe
openlabs_sale_channel.egg-info/requires.txt
openlabs_sale_channel.egg-info/top_level.txt